log/__init__.py
xingchen_log-0.0.1.dist-info/LICENSE
xingchen_log-0.0.1.dist-info/METADATA
xingchen_log-0.0.1.dist-info/WHEEL
xingchen_log-0.0.1.dist-info/top_level.txt
xingchen_log-0.0.1.dist-info/RECORD
