Metadata-Version: 2.1
Name: xingchen-log
Version: 0.0.1
Summary: 一个轻量，简易的Python日志记录模块。
Author-email: YeyingXingchen <yeyingxingchen@yeah.net>
License: MIT License
Project-URL: Repository, https://github.com/XingchenOpenSource/xingchen-log.git
Project-URL: Bug Tracker, https://github.com/XingchenOpenSource/xingchen-log/issues
Keywords: todaydiscourse,discourse,api
Requires-Python: >=3.12
License-File: LICENSE
